MANIFEST.in
README.txt
license.txt
setup.cfg
setup.py
./__init__.py
./quisk_hardware_fldigi.py
./quisk_hardware_k3.py
./quisk_hardware_lppan.py
quisk_lppan_k3.egg-info/PKG-INFO
quisk_lppan_k3.egg-info/SOURCES.txt
quisk_lppan_k3.egg-info/dependency_links.txt
quisk_lppan_k3.egg-info/not-zip-safe
quisk_lppan_k3.egg-info/requires.txt
quisk_lppan_k3.egg-info/top_level.txt