Metadata-Version: 1.0
Name: quisk-lppan-k3
Version: 0.1.2
Summary: Hardware support for QUISK for the Elecraft K3, LP-PAN Panadapter, and fldigi
Home-page: http://wa5znu.org/2009/04/quisk-lppan-k3/
Author: Leigh L. Klotz, Jr.
Author-email: Leigh@WA5ZNU.org
License: GPL
Platform: POSIX
Classifier: Development Status :: 3 - Alpha
Classifier: Environment :: X11 Applications
Classifier: Intended Audience :: End Users/Desktop
Classifier: License :: OSI Approved :: GNU General Public License (GPL)
Classifier: Natural Language :: English
Classifier: Operating System :: POSIX
Classifier: Programming Language :: Python
Classifier: Topic :: Communications :: Ham Radio
